{
  "base_stats": [
    {
      "type": "FLAT",
      "max": 20.0,
      "min": 10.0,
      "stat": "magic_shield"
    }
  ],
  "gear_slot": "pants",
  "guid": "cloth_pants",
  "possible_items": [
    {
      "item_id": "lowlands_clothing:mountainmenclothes_leggings",
      "min_rar": "common",
      "weight": 1
    },
    {
      "item_id": "irons_spellbooks:wandering_magician_leggings",
      "min_rar": "uncommon",
      "weight": 10
    },
    {
      "item_id": "irons_spellbooks:pumpkin_chestplate",
      "min_rar": "rare",
      "weight": 100
    }
  ],
  "req": {
    "base_req": {},
    "scaling_req": {
      "intelligence": 0.4
    }
  },
  "style": "INT",
  "tags": {
    "tags": [
      "armor_family",
      "pants",
      "magic_shield_stat",
      "intelligence",
	  "cloth_pants",
	  "cloth"
    ]
  },
  "weapon_type": "none",
  "weight": 1000
}